hermes/__init__.py
hermes/aeriel/client/__init__.py
hermes/aeriel/client/client.py
hermes/aeriel/monitor/__init__.py
hermes/aeriel/monitor/logging.py
hermes/aeriel/monitor/monitor.py
hermes/aeriel/monitor/process.py
hermes/aeriel/monitor/utils.py
hermes/aeriel/serve/__init__.py
hermes/aeriel/serve/serve.py
hermes/quiver/__init__.py
hermes/quiver/model.py
hermes/quiver/model_config.py
hermes/quiver/model_repository.py
hermes/quiver/platform.py
hermes/quiver/types.py
hermes/quiver/exporters/__init__.py
hermes/quiver/exporters/ensemble.py
hermes/quiver/exporters/exporter.py
hermes/quiver/exporters/keras_savedmodel.py
hermes/quiver/exporters/torch_onnx.py
hermes/quiver/exporters/torch_tensorrt.py
hermes/quiver/exporters/torchscript.py
hermes/quiver/exporters/utils.py
hermes/quiver/exporters/tensorrt/__init__.py
hermes/quiver/exporters/tensorrt/onnx.py
hermes/quiver/io/__init__.py
hermes/quiver/io/exceptions.py
hermes/quiver/io/file_system.py
hermes/quiver/io/gcs.py
hermes/quiver/io/local.py
hermes/quiver/streaming/__init__.py
hermes/quiver/streaming/streaming_input.py
hermes/quiver/streaming/streaming_output.py
hermes/quiver/streaming/utils.py
ml4gw_hermes-0.2.2.dist-info/licenses/LICENSE
ml4gw_hermes-0.2.2.dist-info/METADATA
ml4gw_hermes-0.2.2.dist-info/WHEEL
ml4gw_hermes-0.2.2.dist-info/top_level.txt
ml4gw_hermes-0.2.2.dist-info/RECORD
