Metadata-Version: 2.4
Name: ml4gw-hermes
Version: 0.2.2
Summary: Inference-as-a-Service deployment made simple
Author-email: Alec Gunny <alec.gunny@ligo.org>, Ethan Marx <emarx@mit.edu>
Requires-Python: <3.13,>=3.9
License-File: LICENSE
Requires-Dist: tritonclient[all]~=2.22
Requires-Dist: numpy~=1.22
Requires-Dist: spython<0.3,>=0.2
Requires-Dist: tblib~=1.7
Requires-Dist: protobuf~=3.17
Requires-Dist: requests<3,>=2.26.0
Provides-Extra: tensorflow
Requires-Dist: tensorflow<2.17; extra == "tensorflow"
Requires-Dist: tf-keras<2.17,>=2.16; extra == "tensorflow"
Provides-Extra: torch
Requires-Dist: torch~=2.0; extra == "torch"
Requires-Dist: onnx<2,>=1.15.0; extra == "torch"
Requires-Dist: urllib3~=1.26; extra == "torch"
Requires-Dist: onnxscript; extra == "torch"
Provides-Extra: gcs
Requires-Dist: google-cloud-storage~=1.38; extra == "gcs"
Provides-Extra: tensorrt
Requires-Dist: nvidia-tensorrt~=8.0; extra == "tensorrt"
Dynamic: license-file
